kookvoice/__init__.py
kookvoice/kookvoice.py
kookvoice/requestor.py
kookvoice/voice.py
kookvoice/voice_json.py
kookvoice-0.1.0.dist-info/LICENSE
kookvoice-0.1.0.dist-info/METADATA
kookvoice-0.1.0.dist-info/WHEEL
kookvoice-0.1.0.dist-info/top_level.txt
kookvoice-0.1.0.dist-info/RECORD
