Metadata-Version: 2.1
Name: kookvoice
Version: 0.1.0
Summary: A Python SDK for kook music bot
Home-page: https://github.com/Edint386/simple-kook-voice
Author: xsNight
Author-email: jason62570127@gmail.com
Classifier: Programming Language :: Python :: 3
Classifier: License :: OSI Approved :: MIT License
Classifier: Operating System :: OS Independent
Requires-Python: >=3.8
License-File: LICENSE
Requires-Dist: aiohttp
